cobol_mcp/__init__.py
cobol_mcp/cli.py
cobol_mcp/server.py
cobol_mcp/setup.py
cobol_mcp/resources/context.md
cobol_mcp/resources/gnucobol.md
cobol_mcp/resources/rules.md
cobol_mcp/resources/translate/cics_patterns.md
cobol_mcp/resources/translate/common_pitfalls.md
cobol_mcp/resources/translate/data_type_mappings.md
cobol_mcp/resources/translate/overview.md
cobol_mcp/rules/__init__.py
cobol_mcp/rules/general.py
cobol_mcp/rules/ims.py
cobol_mcp/rules/lookup.py
cobol_mcp/rules/models.py
cobol_mcp/rules/parser.py
cobol_mcp/tools/__init__.py
cobol_mcp/tools/check.py
cobol_mcp/tools/search.py
cobol_mcp/tools/search_migration.py
cobol_mcp/tools/translate.py
cobol_mcp_client-0.1.17.dist-info/METADATA
cobol_mcp_client-0.1.17.dist-info/WHEEL
cobol_mcp_client-0.1.17.dist-info/entry_points.txt
cobol_mcp_client-0.1.17.dist-info/RECORD
