Metadata-Version: 2.4
Name: cobol-mcp-client
Version: 0.1.17
Summary: COBOL MCP server with hybrid search and blind-spot detection
Requires-Python: >=3.10
Requires-Dist: httpx>=0.25
Requires-Dist: mcp>=1.0
